georss_ign_sismologia_client/__init__.py
georss_ign_sismologia_client/__version__.py
georss_ign_sismologia_client/feed.py
georss_ign_sismologia_client/feed_entry.py
georss_ign_sismologia_client/feed_manager.py
georss_ign_sismologia_client-0.7.dist-info/LICENSE
georss_ign_sismologia_client-0.7.dist-info/METADATA
georss_ign_sismologia_client-0.7.dist-info/WHEEL
georss_ign_sismologia_client-0.7.dist-info/top_level.txt
georss_ign_sismologia_client-0.7.dist-info/RECORD
